fidelity_helper/__init__.py
fidelity_helper/fidelity.py
fidelity_helper/fidelity_models.py
fidelity_helper/py.typed
fidelity_helper/fidelity-templates/getAccountsOptions.json
fidelity_helper/fidelity-templates/getTransactionsBody.json.mustache
fidelity_helper/fidelity-templates/getTransactionsOptions.json.mustache
fidelity_helper-0.1.1.dist-info/METADATA
fidelity_helper-0.1.1.dist-info/WHEEL
fidelity_helper-0.1.1.dist-info/licenses/LICENSE
fidelity_helper-0.1.1.dist-info/RECORD
