Metadata-Version: 2.4
Name: fidelity-helper
Version: 0.1.1
Summary: Fetch Fidelity transactions
Project-URL: Homepage, https://github.com/righteffort/finance-helper/tree/main/python/fidelity-helper
Project-URL: Source, https://github.com/righteffort/finance-helper.git
Project-URL: Documentation, https://righteffort.github.io/finance-helper/python/fidelity-helper
Project-URL: Issues, https://github.com/righteffort/finance-helper/issues
Author-email: Ted Romer <tromer@gmail.com>
License-Expression: MIT
License-File: LICENSE
Keywords: banking,fidelity,finance
Classifier: Operating System :: OS Independent
Classifier: Programming Language :: Python :: 3
Requires-Python: >=3.10
Requires-Dist: pydantic>=2.12.5
Requires-Dist: pystache>=0.6.8
